rtl/pe.v
//============================================================================
// Module: Processing Element (PE)
// Description: Fundamental MAC (Multiply-Accumulate) unit for systolic array.
//              Each PE performs: acc += a_in * b_in
//              Data flows: a_in → a_out (right), b_in → b_out (down)
//
// Parameters:
//   DATA_WIDTH - Bit width of input operands (default: 8 for INT8)
//   ACC_WIDTH  - Bit width of accumulator (default: 32)
//
// Author: AI Accelerator Project
//============================================================================

module pe #(
    parameter DATA_WIDTH = 8,
    parameter ACC_WIDTH  = 32
)(
    input  wire                    clk,
    input  wire                    rst_n,      // Active-low reset
    input  wire                    en,         // Enable signal
    input  wire                    clear_acc,  // Clear accumulator
    input  wire [DATA_WIDTH-1:0]   a_in,       // Input from left
    input  wire [DATA_WIDTH-1:0]   b_in,       // Input from top
    output reg  [DATA_WIDTH-1:0]   a_out,      // Output to right
    output reg  [DATA_WIDTH-1:0]   b_out,      // Output to bottom
    output reg  [ACC_WIDTH-1:0]    acc          // Accumulated result
);

    // Internal product wire
    wire [2*DATA_WIDTH-1:0] product;
    
    // Multiply: a_in * b_in (unsigned multiplication)
    assign product = a_in * b_in;

    // Sequential logic: MAC operation + data forwarding
    always @(posedge clk or negedge rst_n) begin
        if (!rst_n) begin
            a_out <= {DATA_WIDTH{1'b0}};
            b_out <= {DATA_WIDTH{1'b0}};
            acc   <= {ACC_WIDTH{1'b0}};
        end else if (clear_acc) begin
            acc   <= {ACC_WIDTH{1'b0}};
            a_out <= {DATA_WIDTH{1'b0}};
            b_out <= {DATA_WIDTH{1'b0}};
        end else if (en) begin
            // MAC: accumulate product (sign-extend for proper width)
            acc   <= acc + {{(ACC_WIDTH-2*DATA_WIDTH){1'b0}}, product};
            // Forward data to neighbors
            a_out <= a_in;  // Pass A to the right
            b_out <= b_in;  // Pass B downward
        end
    end

endmodule

sim/tb_pe.v
//============================================================================
// Testbench: Processing Element (PE)
// Description: Verifies MAC operation, data forwarding, reset, and
//              accumulator clear functionality of a single PE.
//
// Author: AI Accelerator Project
//============================================================================

`timescale 1ns / 1ps

module tb_pe;

    //------------------------------------------------------------------------
    // Parameters
    //------------------------------------------------------------------------
    parameter DATA_WIDTH = 8;
    parameter ACC_WIDTH  = 32;
    parameter CLK_PERIOD = 10;  // 100 MHz

    //------------------------------------------------------------------------
    // Signals
    //------------------------------------------------------------------------
    reg                    clk;
    reg                    rst_n;
    reg                    en;
    reg                    clear_acc;
    reg  [DATA_WIDTH-1:0]  a_in;
    reg  [DATA_WIDTH-1:0]  b_in;
    wire [DATA_WIDTH-1:0]  a_out;
    wire [DATA_WIDTH-1:0]  b_out;
    wire [ACC_WIDTH-1:0]   acc;

    //------------------------------------------------------------------------
    // DUT Instantiation
    //------------------------------------------------------------------------
    pe #(
        .DATA_WIDTH(DATA_WIDTH),
        .ACC_WIDTH(ACC_WIDTH)
    ) dut (
        .clk       (clk),
        .rst_n     (rst_n),
        .en        (en),
        .clear_acc (clear_acc),
        .a_in      (a_in),
        .b_in      (b_in),
        .a_out     (a_out),
        .b_out     (b_out),
        .acc       (acc)
    );

    //------------------------------------------------------------------------
    // Clock Generation
    //------------------------------------------------------------------------
    initial clk = 0;
    always #(CLK_PERIOD/2) clk = ~clk;

    //------------------------------------------------------------------------
    // Test Variables
    //------------------------------------------------------------------------
    integer test_pass = 0;
    integer test_fail = 0;
    integer total_tests = 0;
    reg [ACC_WIDTH-1:0] expected_acc;

    //------------------------------------------------------------------------
    // Task: Check Result
    //------------------------------------------------------------------------
    task check_result;
        input [ACC_WIDTH-1:0] expected;
        input [255:0] test_name;  // Use fixed-width for Verilog compatibility
    begin
        total_tests = total_tests + 1;
        if (acc === expected) begin
            $display("[PASS] %0s: acc = %0d (expected %0d)", test_name, acc, expected);
            test_pass = test_pass + 1;
        end else begin
            $display("[FAIL] %0s: acc = %0d (expected %0d)", test_name, acc, expected);
            test_fail = test_fail + 1;
        end
    end
    endtask

    //------------------------------------------------------------------------
    // Test Stimulus
    //------------------------------------------------------------------------
    initial begin
        $display("============================================");
        $display("  PE Testbench - Starting Tests");
        $display("============================================");
        
        // Initialize
        rst_n     = 0;
        en        = 0;
        clear_acc = 0;
        a_in      = 0;
        b_in      = 0;
        
        // Reset
        #(CLK_PERIOD * 3);
        rst_n = 1;
        #(CLK_PERIOD);
        
        //--------------------------------------------------------------------
        // Test 1: Basic MAC operation (3 × 4 = 12)
        //--------------------------------------------------------------------
        $display("\n--- Test 1: Basic MAC (3 x 4) ---");
        en   = 1;
        a_in = 8'd3;
        b_in = 8'd4;
        @(posedge clk); #1;
        check_result(32'd12, "Basic MAC 3x4");
        
        //--------------------------------------------------------------------
        // Test 2: Accumulation (12 + 5 × 6 = 42)
        //--------------------------------------------------------------------
        $display("\n--- Test 2: Accumulation (+ 5 x 6) ---");
        a_in = 8'd5;
        b_in = 8'd6;
        @(posedge clk); #1;
        check_result(32'd42, "Accumulate 5x6");
        
        //--------------------------------------------------------------------
        // Test 3: Data forwarding check
        //--------------------------------------------------------------------
        $display("\n--- Test 3: Data Forwarding ---");
        a_in = 8'd7;
        b_in = 8'd8;
        @(posedge clk); #1;
        total_tests = total_tests + 1;
        if (a_out === 8'd7 && b_out === 8'd8) begin
            $display("[PASS] Data forwarding: a_out=%0d, b_out=%0d", a_out, b_out);
            test_pass = test_pass + 1;
        end else begin
            $display("[FAIL] Data forwarding: a_out=%0d (exp 7), b_out=%0d (exp 8)", a_out, b_out);
            test_fail = test_fail + 1;
        end
        
        //--------------------------------------------------------------------
        // Test 4: Enable gating (acc should not change when en=0)
        //--------------------------------------------------------------------
        $display("\n--- Test 4: Enable Gating ---");
        expected_acc = acc;  // Save current value
        en   = 0;
        a_in = 8'd100;
        b_in = 8'd100;
        @(posedge clk); #1;
        check_result(expected_acc, "Enable gating");
        
        //--------------------------------------------------------------------
        // Test 5: Clear accumulator
        //--------------------------------------------------------------------
        $display("\n--- Test 5: Clear Accumulator ---");
        en        = 0;
        clear_acc = 1;
        @(posedge clk); #1;
        check_result(32'd0, "Clear accumulator");
        clear_acc = 0;
        
        //--------------------------------------------------------------------
        // Test 6: Multiple MACs (dot product simulation)
        // Compute: 1*1 + 2*2 + 3*3 + 4*4 = 1 + 4 + 9 + 16 = 30
        //--------------------------------------------------------------------
        $display("\n--- Test 6: Dot Product (1*1 + 2*2 + 3*3 + 4*4 = 30) ---");
        en = 1;
        
        a_in = 8'd1; b_in = 8'd1;
        @(posedge clk); #1;
        
        a_in = 8'd2; b_in = 8'd2;
        @(posedge clk); #1;
        
        a_in = 8'd3; b_in = 8'd3;
        @(posedge clk); #1;
        
        a_in = 8'd4; b_in = 8'd4;
        @(posedge clk); #1;
        
        check_result(32'd30, "Dot product");
        
        //--------------------------------------------------------------------
        // Test 7: Max value test (255 × 255 = 65025)
        //--------------------------------------------------------------------
        $display("\n--- Test 7: Max Value (255 x 255) ---");
        clear_acc = 1;
        @(posedge clk); #1;
        clear_acc = 0;
        
        en   = 1;
        a_in = 8'd255;
        b_in = 8'd255;
        @(posedge clk); #1;
        check_result(32'd65025, "Max value 255x255");
        
        //--------------------------------------------------------------------
        // Test 8: Reset during operation
        //--------------------------------------------------------------------
        $display("\n--- Test 8: Reset During Operation ---");
        a_in = 8'd10;
        b_in = 8'd10;
        @(posedge clk); #1;
        
        // Apply reset and check accumulator is cleared
        rst_n = 0;
        @(posedge clk); #1;
        total_tests = total_tests + 1;
        if (acc === 32'd0) begin
            $display("[PASS] Reset clears acc: acc = %0d (expected 0)", acc);
            test_pass = test_pass + 1;
        end else begin
            $display("[FAIL] Reset clears acc: acc = %0d (expected 0)", acc);
            test_fail = test_fail + 1;
        end
        
        // Release reset and verify normal operation resumes
        rst_n = 1;
        @(posedge clk); #1;
        check_result(32'd100, "Operation resumes after reset");
        
        //--------------------------------------------------------------------
        // Summary
        //--------------------------------------------------------------------
        #(CLK_PERIOD * 2);
        $display("\n============================================");
        $display("  PE Testbench - Results Summary");
        $display("============================================");
        $display("  Total Tests: %0d", total_tests);
        $display("  Passed:      %0d", test_pass);
        $display("  Failed:      %0d", test_fail);
        $display("============================================");
        
        if (test_fail == 0)
            $display("  >>> ALL TESTS PASSED <<<");
        else
            $display("  >>> SOME TESTS FAILED <<<");
        
        $display("============================================\n");
        $finish;
    end

    //------------------------------------------------------------------------
    // Waveform Dump
    //------------------------------------------------------------------------
    initial begin
        $dumpfile("tb_pe.vcd");
        $dumpvars(0, tb_pe);
    end

endmodule

sim/tb_pe.vcd
$date
	Thu Mar 19 03:44:15 2026
$end
$version
	Icarus Verilog
$end
$timescale
	1ps
$end
$scope module tb_pe $end
$var wire 8 ! b_out [7:0] $end
$var wire 32 " acc [31:0] $end
$var wire 8 # a_out [7:0] $end
$var parameter 32 $ ACC_WIDTH $end
$var parameter 32 % CLK_PERIOD $end
$var parameter 32 & DATA_WIDTH $end
$var reg 8 ' a_in [7:0] $end
$var reg 8 ( b_in [7:0] $end
$var reg 1 ) clear_acc $end
$var reg 1 * clk $end
$var reg 1 + en $end
$var reg 32 , expected_acc [31:0] $end
$var reg 1 - rst_n $end
$var integer 32 . test_fail [31:0] $end
$var integer 32 / test_pass [31:0] $end
$var integer 32 0 total_tests [31:0] $end
$scope module dut $end
$var wire 8 1 a_in [7:0] $end
$var wire 8 2 b_in [7:0] $end
$var wire 1 ) clear_acc $end
$var wire 1 * clk $end
$var wire 1 + en $end
$var wire 1 - rst_n $end
$var wire 16 3 product [15:0] $end
$var parameter 32 4 ACC_WIDTH $end
$var parameter 32 5 DATA_WIDTH $end
$var reg 8 6 a_out [7:0] $end
$var reg 32 7 acc [31:0] $end
$var reg 8 8 b_out [7:0] $end
$upscope $end
$scope task check_result $end
$var reg 32 9 expected [31:0] $end
$var reg 256 : test_name [255:0] $end
$upscope $end
$upscope $end
$enddefinitions $end
$comment Show the parameter values. $end
$dumpall
b1000 5
b100000 4
b1000 &
b1010 %
b100000 $
$end
#0
$dumpvars
bx :
bx 9
b0 8
b0 7
b0 6
b0 3
b0 2
b0 1
b0 0
b0 /
b0 .
0-
bx ,
0+
0*
0)
b0 (
b0 '
b0 #
b0 "
b0 !
$end
#5000
1*
#10000
0*
#15000
1*
#20000
0*
#25000
1*
#30000
0*
1-
#35000
1*
#40000
0*
b1100 3
b100 (
b100 2
b11 '
b11 1
1+
#45000
b100 !
b100 8
b11 #
b11 6
b1100 "
b1100 7
1*
#46000
b110 (
b110 2
b11110 3
b101 '
b101 1
b1 /
b1 0
b1000010011000010111001101101001011000110010000001001101010000010100001100100000001100110111100000110100 :
b1100 9
#50000
0*
#55000
b110 !
b110 8
b101 #
b101 6
b101010 "
b101010 7
1*
#56000
b1000 (
b1000 2
b111000 3
b111 '
b111 1
b10 /
b10 0
b100000101100011011000110111010101101101011101010110110001100001011101000110010100100000001101010111100000110110 :
b101010 9
#60000
0*
#65000
b1000 !
b1000 8
b111 #
b111 6
b1100010 "
b1100010 7
1*
#66000
b1100100 (
b1100100 2
b10011100010000 3
b1100100 '
b1100100 1
0+
b1100010 ,
b11 /
b11 0
#70000
0*
#75000
1*
#76000
1)
b100 /
b100 0
b1000101011011100110000101100010011011000110010100100000011001110110000101110100011010010110111001100111 :
b1100010 9
#80000
0*
#85000
b0 !
b0 8
b0 #
b0 6
b0 "
b0 7
1*
#86000
b1 (
b1 2
b1 3
b1 '
b1 1
1+
0)
b101 /
b101 0
b100001101101100011001010110000101110010001000000110000101100011011000110111010101101101011101010110110001100001011101000110111101110010 :
b0 9
#90000
0*
#95000
b1 !
b1 8
b1 #
b1 6
b1 "
b1 7
1*
#96000
b10 (
b10 2
b100 3
b10 '
b10 1
#100000
0*
#105000
b10 !
b10 8
b10 #
b10 6
b101 "
b101 7
1*
#106000
b11 (
b11 2
b1001 3
b11 '
b11 1
#110000
0*
#115000
b11 !
b11 8
b11 #
b11 6
b1110 "
b1110 7
1*
#116000
b100 (
b100 2
b10000 3
b100 '
b100 1
#120000
0*
#125000
b100 !
b100 8
b100 #
b100 6
b11110 "
b11110 7
1*
#126000
1)
b110 /
b110 0
b100010001101111011101000010000001110000011100100110111101100100011101010110001101110100 :
b11110 9
#130000
0*
#135000
b0 !
b0 8
b0 #
b0 6
b0 "
b0 7
1*
#136000
b11111111 (
b11111111 2
b1111111000000001 3
b11111111 '
b11111111 1
0)
#140000
0*
#145000
b11111111 !
b11111111 8
b11111111 #
b11111111 6
b1111111000000001 "
b1111111000000001 7
1*
#146000
b1010 (
b1010 2
b1100100 3
b1010 '
b1010 1
b111 /
b111 0
b100110101100001011110000010000001110110011000010110110001110101011001010010000000110010001101010011010101111000001100100011010100110101 :
b1111111000000001 9
#150000
0*
#155000
b1010 !
b1010 8
b1010 #
b1010 6
b1111111001100101 "
b1111111001100101 7
1*
#156000
b0 "
b0 7
b0 !
b0 8
b0 #
b0 6
0-
#160000
0*
#165000
1*
#166000
1-
b1000 /
b1000 0
#170000
0*
#175000
b1010 !
b1010 8
b1010 #
b1010 6
b1100100 "
b1100100 7
1*
#176000
b1001 /
b1001 0
b100111101110000011001010111001001100001011101000110100101101111011011100010000001110010011001010111001101110101011011010110010101110011001000000110000101100110011101000110010101110010001000000111001001100101011100110110010101110100 :
b1100100 9
#180000
0*
#185000
b11001000 "
b11001000 7
1*
#190000
0*
#195000
b100101100 "
b100101100 7
1*
